socker/__init__.py
socker/__main__.py
socker/auth.py
socker/handlers.py
socker/router.py
socker/server.py
socker/tools.py
socker/transport.py
socker/tree.py
socker/cli/__init__.py
socker/cli/colors.py
socker/cli/command.py
socker/cli/log.py
socker-2.1.0.dist-info/METADATA
socker-2.1.0.dist-info/WHEEL
socker-2.1.0.dist-info/entry_points.txt
socker-2.1.0.dist-info/top_level.txt
socker-2.1.0.dist-info/RECORD
