Metadata-Version: 2.2
Name: socker
Version: 2.1.0
Summary: redis pubsub websocket proxy
Home-page: https://github.com/5monkeys/socker
Author: Joar Wandborg
Author-email: joar@5monkeys.se
License: MIT
Requires-Dist: asyncio-redis~=0.16.0
Requires-Dist: websockets~=15.0.1
Requires-Dist: docopt>=0.6.2
Requires-Dist: Werkzeug~=3.1.3
Requires-Dist: semver~=3.0.4
Dynamic: author
Dynamic: author-email
Dynamic: description
Dynamic: home-page
Dynamic: license
Dynamic: requires-dist
Dynamic: summary
